fibers/__init__.py
fibers/_cfibers.cp36-win32.pyd
fibers/_pyfibers.py
fibers-1.1.0.dist-info/DESCRIPTION.rst
fibers-1.1.0.dist-info/METADATA
fibers-1.1.0.dist-info/RECORD
fibers-1.1.0.dist-info/WHEEL
fibers-1.1.0.dist-info/metadata.json
fibers-1.1.0.dist-info/top_level.txt
