Metadata-Version: 1.1
Name: fibers
Version: 1.1.0
Summary: Lightweight cooperative microthreads for Pyhton
Home-page: http://github.com/saghul/python-fibers
Author: Saúl Ibarra Corretgé
Author-email: saghul@gmail.com
License: UNKNOWN
Platform: POSIX
Platform: Microsoft Windows
Classifier: Development Status :: 5 - Production/Stable
Classifier: Intended Audience :: Developers
Classifier: License :: OSI Approved :: MIT License
Classifier: Operating System :: POSIX
Classifier: Operating System :: Microsoft :: Windows
Classifier: Programming Language :: Python
Classifier: Programming Language :: Python :: 2
Classifier: Programming Language :: Python :: 2.7
Classifier: Programming Language :: Python :: 3
Classifier: Programming Language :: Python :: 3.3
Classifier: Programming Language :: Python :: 3.4
Classifier: Programming Language :: Python :: Implementation :: CPython
Classifier: Programming Language :: Python :: Implementation :: PyPy
